u_transkript/__init__.py
u_transkript/ai_translator.py
u_transkript/exceptions.py
u_transkript/fetched_transcript.py
u_transkript/formatters.py
u_transkript/transcript_list.py
u_transkript/utils.py
u_transkript/youtube_transcript.py
u_transkript-1.1.0.dist-info/METADATA
u_transkript-1.1.0.dist-info/WHEEL
u_transkript-1.1.0.dist-info/top_level.txt
u_transkript-1.1.0.dist-info/RECORD
